etiketti/__init__.py
etiketti/__main__.py
etiketti/cli.py
etiketti/discover.py
etiketti/implementation.py
etiketti-2025.6.8.dist-info/licenses/LICENSE
example/etiketti.yml
example/label_per_env.py
etiketti-2025.6.8.dist-info/METADATA
etiketti-2025.6.8.dist-info/WHEEL
etiketti-2025.6.8.dist-info/entry_points.txt
etiketti-2025.6.8.dist-info/top_level.txt
etiketti-2025.6.8.dist-info/RECORD
