Metadata-Version: 2.4
Name: etiketti
Version: 2025.6.8
Summary: Label (Finnish: etiketti) some files.
Author-email: Stefan Hagen <stefan@hagen.link>
Maintainer-email: Stefan Hagen <stefan@hagen.link>
License: Mozilla Public License Version 2.0
Project-URL: Homepage, https://git.sr.ht/~sthagen/etiketti
Project-URL: Bug-Tracker, https://todo.sr.ht/~sthagen/etiketti
Project-URL: Documentation, https://codes.dilettant.life/docs/etiketti
Project-URL: Source-Code, https://git.sr.ht/~sthagen/etiketti
Project-URL: Test-Coverage, https://codes.dilettant.life/coverage/etiketti
Keywords: developer-tools,devops
Classifier: Development Status :: 3 - Alpha
Classifier: Intended Audience :: Developers
Classifier: License :: OSI Approved :: Mozilla Public License 2.0 (MPL 2.0)
Classifier: Programming Language :: Python :: 3.10
Classifier: Programming Language :: Python :: 3.11
Classifier: Programming Language :: Python :: 3.12
Classifier: Programming Language :: Python :: 3.13
Classifier: Programming Language :: Python :: 3.9
Requires-Python: >=3.9
License-File: LICENSE
Requires-Dist: PyYAML>=6.0
Requires-Dist: liitos>=2023.6.17
Requires-Dist: navigaattori>=2023.6.18
Requires-Dist: pikepdf>=6.2.8.post1
Provides-Extra: dev
Requires-Dist: black; extra == "dev"
Requires-Dist: coverage; extra == "dev"
Requires-Dist: hypothesis; extra == "dev"
Requires-Dist: mypy; extra == "dev"
Requires-Dist: pytest; extra == "dev"
Requires-Dist: pytest-cov; extra == "dev"
Requires-Dist: pytest-flake8; extra == "dev"
Requires-Dist: ruff; extra == "dev"
Dynamic: license-file
